visualize_volume/__init__.py
visualize_volume/test_data_gen.py
visualize_volume/visualize.py
visualize_volume-0.0.4.dist-info/licenses/LICENSE
visualize_volume-0.0.4.dist-info/METADATA
visualize_volume-0.0.4.dist-info/WHEEL
visualize_volume-0.0.4.dist-info/top_level.txt
visualize_volume-0.0.4.dist-info/RECORD
