Metadata-Version: 2.4
Name: visualize_volume
Version: 0.0.4
Summary: Visualize 3D volume data.
Author-email: GGN_2015 <neko@jlulug.org>
License-Expression: MIT
Requires-Python: <3.13,>=3.10
License-File: LICENSE
Requires-Dist: numpy
Requires-Dist: vtk
Dynamic: license-file
